NetkillerRadio/README.md
NetkillerRadio/__init__.py
NetkillerRadio/__main__.py
NetkillerRadio/file.epub
NetkillerRadio/index.html
NetkillerRadio/css/__init__.py
NetkillerRadio/css/annotations.css
NetkillerRadio/css/main.css
NetkillerRadio/css/normalize.css
NetkillerRadio/css/popup.css
NetkillerRadio/font/__init__.py
NetkillerRadio/font/fontello.eot
NetkillerRadio/font/fontello.svg
NetkillerRadio/font/fontello.ttf
NetkillerRadio/font/fontello.woff
NetkillerRadio/img/__init__.py
NetkillerRadio/img/annotator-glyph-sprite.png
NetkillerRadio/img/annotator-icon-sprite.png
NetkillerRadio/img/apple-touch-icon.png
NetkillerRadio/img/cancelfullscreen.png
NetkillerRadio/img/close.png
NetkillerRadio/img/fullscreen.png
NetkillerRadio/img/loader.gif
NetkillerRadio/img/menu-icon.png
NetkillerRadio/img/save.png
NetkillerRadio/img/saved.png
NetkillerRadio/img/settings-s.png
NetkillerRadio/img/settings.png
NetkillerRadio/img/star.png
NetkillerRadio/js/__init__.py
NetkillerRadio/js/epub.js
NetkillerRadio/js/epub.min.js
NetkillerRadio/js/epub.min.map
NetkillerRadio/js/hooks.min.js
NetkillerRadio/js/hooks.min.map
NetkillerRadio/js/reader.js
NetkillerRadio/js/reader.js.map
NetkillerRadio/js/reader.min.js
NetkillerRadio/js/reader.min.map
NetkillerRadio/js/hooks/__init__.py
NetkillerRadio/js/hooks/extensions/__init__.py
NetkillerRadio/js/hooks/extensions/highlight.js
NetkillerRadio/js/libs/__init__.py
NetkillerRadio/js/libs/jquery.min.js
NetkillerRadio/js/libs/localforage.min.js
NetkillerRadio/js/libs/screenfull.js
NetkillerRadio/js/libs/screenfull.min.js
NetkillerRadio/js/libs/zip.min.js
NetkillerRadio/js/plugins/__init__.py
NetkillerRadio/js/plugins/hypothesis.js
NetkillerRadio/js/plugins/search.js
netkiller_radio-2024.3.5.0.dist-info/METADATA
netkiller_radio-2024.3.5.0.dist-info/WHEEL
netkiller_radio-2024.3.5.0.dist-info/entry_points.txt
netkiller_radio-2024.3.5.0.dist-info/top_level.txt
netkiller_radio-2024.3.5.0.dist-info/RECORD
